clason/__init__.py
Clason-1.0.1.dist-info/LICENSE
Clason-1.0.1.dist-info/METADATA
Clason-1.0.1.dist-info/WHEEL
Clason-1.0.1.dist-info/top_level.txt
Clason-1.0.1.dist-info/RECORD
