Metadata-Version: 2.1
Name: Clason
Version: 1.0.1
Summary: Load your classes with json and save it with json or work with python dictionary's
Home-page: https://github.com/princessmiku/Clason
Author: Miku
Author-email: 
License: MIT
Keywords: json,orm
Classifier: Programming Language :: Python :: 3.10
Requires-Python: >=3.10.0
License-File: LICENSE
